azalea/__init__.py
azalea/datagen.py
azalea/evaluation.py
azalea/experiment.py
azalea/fnv1a.py
azalea/monitor.py
azalea/network.py
azalea/parallel.py
azalea/parallel_datagen.py
azalea/play.py
azalea/policy.py
azalea/policy_trainer.py
azalea/random_policy.py
azalea/ranking.py
azalea/replaybuf.py
azalea/search.py
azalea/search_tree.py
azalea/tuning.py
azalea/utils.py
azalea/version.py
azalea/game/__init__.py
azalea/game/hex.py
azalea/game/term.py
azalea-0.1.0.dist-info/METADATA
azalea-0.1.0.dist-info/RECORD
azalea-0.1.0.dist-info/WHEEL
azalea-0.1.0.dist-info/entry_points.txt
azalea-0.1.0.dist-info/top_level.txt
