Metadata-Version: 2.1
Name: azalea
Version: 0.1.0
Summary: Hex board game AI with self-play learning based on the AlphaZero algorithm
Home-page: https://github.com/jseppanen/azalea
Author: Jarno Seppänen
Author-email: azalea@meit.si
License: BSD 3-Clause License
Platform: UNKNOWN
Classifier: Programming Language :: Python :: 3
Classifier: License :: OSI Approved :: BSD License
Classifier: Operating System :: POSIX :: Linux
Classifier: Operating System :: OS Independent
Requires-Dist: numba
Requires-Dist: numpy
Requires-Dist: torch
Requires-Dist: scipy
Requires-Dist: pyyaml
Requires-Dist: click
Requires-Dist: tensorboardX
